myko_async/__init__.py
myko_async/__init__.py.bak
myko_async/auth.py
myko_async/cli.py
myko_async/connection.py
myko_async/const.py
myko_async/device.py
myko_async/room.py
myko_async-0.4.2.dist-info/METADATA
myko_async-0.4.2.dist-info/WHEEL
myko_async-0.4.2.dist-info/licenses/AUTHORS.rst
myko_async-0.4.2.dist-info/licenses/LICENSE.txt
myko_async-0.4.2.dist-info/RECORD
