Metadata-Version: 2.3
Name: myko-async
Version: 0.4.2
Summary: Talk to the Myko API asynchronously
Project-URL: Repository, https://github.com/Expl0dingBanana/hubspace-async
Project-URL: Changelog, https://github.com/Expl0dingBanana/hubspace-async/CHANGELOG.md
Author-email: Chris Dohmen <chris.dohmen11@gmail.com>
Maintainer: dvd604
License: The MIT License (MIT)
Keywords: Myko
Classifier: Development Status :: 4 - Beta
Classifier: Programming Language :: Python
Classifier: Programming Language :: Python :: 3.10
Classifier: Programming Language :: Python :: 3.11
Classifier: Programming Language :: Python :: 3.12
Requires-Python: >=3.10
Requires-Dist: aiohttp
Requires-Dist: beautifulsoup4
Provides-Extra: cli
Requires-Dist: click; extra == 'cli'
Provides-Extra: test
Requires-Dist: anyio; extra == 'test'
Requires-Dist: pytest; extra == 'test'
Requires-Dist: pytest-aioresponses; extra == 'test'
Requires-Dist: pytest-cov; extra == 'test'
Requires-Dist: pytest-mock; extra == 'test'
